django_ticketbai/__init__.py
django_ticketbai/admin.py
django_ticketbai/apps.py
django_ticketbai/forms.py
django_ticketbai/models.py
django_ticketbai/urls.py
django_ticketbai/validators.py
django_ticketbai/views.py
django_ticketbai/locale/eu/LC_MESSAGES/django.mo
django_ticketbai/locale/eu/LC_MESSAGES/django.po
django_ticketbai/migrations/0001_initial.py
django_ticketbai/migrations/0002_invoice_pdf_invoice_signedxml.py
django_ticketbai/migrations/0003_alter_invoice_pdf_invoiceline.py
django_ticketbai/migrations/0004_invoice_csv_code_invoice_tbai_code_and_more.py
django_ticketbai/migrations/0005_config_alter_invoice_simplified_and_more.py
django_ticketbai/migrations/0006_config_is_active.py
django_ticketbai/migrations/0007_invoice_errorxml.py
django_ticketbai/migrations/0008_remove_invoice_user_invoice_email.py
django_ticketbai/migrations/0009_alter_config_options_alter_invoice_options_and_more.py
django_ticketbai/migrations/0010_alter_invoice_signature_value.py
django_ticketbai/migrations/0011_alter_invoice_signature_value.py
django_ticketbai/migrations/0012_invoice_pre_invoice_alter_invoice_signature_value.py
django_ticketbai/migrations/0013_invoice_vat_breakdown_alter_invoice_pre_invoice.py
django_ticketbai/migrations/0014_config_logo_alter_invoice_email.py
django_ticketbai/migrations/0015_invoice_lang.py
django_ticketbai/migrations/__init__.py
django_ticketbai/templates/PDF/ticketbai.css
django_ticketbai/templates/PDF/ticketbai.html
django_ticketbai/templates/admin/django_ticketbai/app_index.html
django_ticketbai/utils/__init__.py
django_ticketbai/utils/invoice.py
django_ticketbai/utils/pdf.py
django_ticketbai-2.1.dist-info/LICENSE
django_ticketbai-2.1.dist-info/METADATA
django_ticketbai-2.1.dist-info/WHEEL
django_ticketbai-2.1.dist-info/top_level.txt
django_ticketbai-2.1.dist-info/RECORD
