Metadata-Version: 2.1
Name: django-ticketbai
Version: 2.1
Summary: django-ticketbai allows to create, manage, store and send TicketBai invoices to the Basque tax authorities.
Home-page: https://github.com/codesyntax/django-ticketbai
Author: Urtzi Odriozola
Author-email: uodriozola@codesyntax.com
License: Copyright 2023 CodeSyntax
Classifier: Intended Audience :: Developers
Classifier: License :: OSI Approved :: MIT License
Classifier: Programming Language :: Python
Classifier: Programming Language :: Python :: 3
Classifier: Programming Language :: Python :: 3.8
Classifier: Programming Language :: Python :: 3.9
Classifier: Programming Language :: Python :: 3.10
Classifier: Programming Language :: Python :: 3.11
License-File: LICENSE
Requires-Dist: pytbai
Requires-Dist: qrcode
Requires-Dist: weasyprint ==59.0
Requires-Dist: crc8 ==0.2.0
